MANIFEST.in
README.md
setup.py
myria/__init__.py
myria/cluster/__init__.py
myria/cluster/playbooks/__init__.py
myria/cluster/playbooks/ec2_remote_facts.py
myria/cluster/playbooks/remote.yml
myria/cluster/playbooks/group_vars/all
myria/cluster/playbooks/roles/apache2/handlers/main.yml
myria/cluster/playbooks/roles/apache2/tasks/main.yml
myria/cluster/playbooks/roles/basenode/defaults/main.yml
myria/cluster/playbooks/roles/basenode/tasks/main.yml
myria/cluster/playbooks/roles/gae/defaults/main.yml
myria/cluster/playbooks/roles/gae/tasks/main.yml
myria/cluster/playbooks/roles/ganglia-metad/defaults/main.yml
myria/cluster/playbooks/roles/ganglia-metad/handlers/main.yml
myria/cluster/playbooks/roles/ganglia-metad/tasks/main.yml
myria/cluster/playbooks/roles/ganglia-metad/templates/gmetad.conf.j2
myria/cluster/playbooks/roles/ganglia-monitor/defaults/main.yml
myria/cluster/playbooks/roles/ganglia-monitor/handlers/main.yml
myria/cluster/playbooks/roles/ganglia-monitor/tasks/main.yml
myria/cluster/playbooks/roles/ganglia-monitor/templates/device-metrics.cron.d
myria/cluster/playbooks/roles/ganglia-monitor/templates/device-metrics.php
myria/cluster/playbooks/roles/ganglia-monitor/templates/gmond.conf.j2
myria/cluster/playbooks/roles/ganglia-web/defaults/main.yml
myria/cluster/playbooks/roles/ganglia-web/handlers/main.yml
myria/cluster/playbooks/roles/ganglia-web/meta/main.yml
myria/cluster/playbooks/roles/ganglia-web/tasks/main.yml
myria/cluster/playbooks/roles/jupyter/defaults/main.yml
myria/cluster/playbooks/roles/jupyter/handlers/main.yml
myria/cluster/playbooks/roles/jupyter/tasks/main.yml
myria/cluster/playbooks/roles/jupyter/templates/service.conf.j2
myria/cluster/playbooks/roles/myria-python/defaults/main.yml
myria/cluster/playbooks/roles/myria-python/tasks/main.yml
myria/cluster/playbooks/roles/myria-web/defaults/main.yml
myria/cluster/playbooks/roles/myria-web/handlers/main.yml
myria/cluster/playbooks/roles/myria-web/tasks/main.yml
myria_cluster.egg-info/PKG-INFO
myria_cluster.egg-info/SOURCES.txt
myria_cluster.egg-info/dependency_links.txt
myria_cluster.egg-info/entry_points.txt
myria_cluster.egg-info/namespace_packages.txt
myria_cluster.egg-info/not-zip-safe
myria_cluster.egg-info/pbr.json
myria_cluster.egg-info/requires.txt
myria_cluster.egg-info/top_level.txt