Metadata-Version: 1.0
Name: myria-cluster
Version: 0.1.54
Summary: CLI to deploy the Myria parallel database on Amazon EC2
Home-page: https://github.com/uwescience/myria-ec2-ansible/tarball/0.1.54
Author: Tobin Baker
Author-email: tdbaker@cs.washington.edu
License: BSD
Platform: UNKNOWN
